{
	"sussy.fort_balls1": {
		"subtitle": "sussyballs",
		"sounds": [
			{
				"name": "suspicious:sussy_balls",
				"stream": true
			}
		]
	},
	"sussy.interstellar": {
		"subtitle": "interstellar",
		"sounds": [
			{
				"name": "suspicious:music/interstellar",
				"stream": true
			}
		]
	},
	"sussy.kendrick_adhd": {
		"subtitle": "kendrick got adhd",
		"sounds": [
			{
				"name": "suspicious:music/kendrick_adhd",
				"stream": true
			}
		]
	},
	"sussy.bjork_sus1": {
		"subtitle": "bjork susy balls",
		"sounds": [
			{
				"name": "suspicious:music/bjork_sus1",
				"stream": true
			}
		]
	},
	"sussy.fortnitesusballsabstract": {
		"subtitle": "how fornite has failed society",
		"sounds": [
			{
				"name": "suspicious:fortnitesusballsabstract",
				"stream": true
			}
		]
	},
	"sussy.transportchicken.receiver_receive": {
		"subtitle": "transport chicken receive",
		"sounds": [
			"suspicious:transportchicken/receiver_receive"
		]
	},
	"sussy.transportchicken.user_activate": {
		"subtitle": "transport chicken send",
		"sounds": [
			"suspicious:transportchicken/user_activate"
		]
	}
}